gtm.py
setup.py
gtm.egg-info/PKG-INFO
gtm.egg-info/SOURCES.txt
gtm.egg-info/dependency_links.txt
gtm.egg-info/top_level.txt