Metadata-Version: 1.1
Name: gtm
Version: 1.0.0
Summary: Bindings to GT.M database.
Home-page: https://github.com/OSEHRA-Sandbox/m.js
Author: OSEHRA
Author-email: ibanezl@osehra.org
License: Apache
Download-URL: https://github.com/OSEHR/m.js
Keywords: GT.M database
Platform: UNKNOWN
Classifier: License :: OSI Approved :: Apache Software License
Classifier: Programming Language :: Python
Classifier: Development Status :: 4 - Beta
Classifier: Intended Audience :: Developers
Classifier: Topic :: Scientific/Engineering
